setup.py
gips/GeoVector.py
gips/__init__.py
gips/algorithm.py
gips/atmosphere.py
gips/core.py
gips/inventory.py
gips/mapreduce.py
gips/parsers.py
gips/settings_template.py
gips/tiles.py
gips/user_settings_template.py
gips/utils.py
gips/version.py
gips.egg-info/PKG-INFO
gips.egg-info/SOURCES.txt
gips.egg-info/dependency_links.txt
gips.egg-info/entry_points.txt
gips.egg-info/requires.txt
gips.egg-info/top_level.txt
gips/data/__init__.py
gips/data/core.py
gips/data/aod/__init__.py
gips/data/aod/aod.py
gips/data/cdl/__init__.py
gips/data/cdl/cdl.py
gips/data/daymet/__init__.py
gips/data/daymet/daymet.py
gips/data/landsat/__init__.py
gips/data/landsat/landsat.py
gips/data/landsat/tiles.dbf
gips/data/landsat/tiles.prj
gips/data/landsat/tiles.shp
gips/data/landsat/tiles.shx
gips/data/merra/__init__.py
gips/data/merra/merra.py
gips/data/merra/tiles.dbf
gips/data/merra/tiles.prj
gips/data/merra/tiles.shp
gips/data/merra/tiles.shx
gips/data/modis/__init__.py
gips/data/modis/modis.py
gips/data/modis/tiles.dbf
gips/data/modis/tiles.prj
gips/data/modis/tiles.shp
gips/data/modis/tiles.shx
gips/data/sar/__init__.py
gips/data/sar/sar.py
gips/data/sar/tiles.dbf
gips/data/sar/tiles.prj
gips/data/sar/tiles.shp
gips/data/sar/tiles.shx
gips/data/sarannual/__init__.py
gips/data/sarannual/sarannual.py
gips/scripts/__init__.py
gips/scripts/archive.py
gips/scripts/info.py
gips/scripts/inventory.py
gips/scripts/mask.py
gips/scripts/process.py
gips/scripts/project.py
gips/scripts/stats.py
gips/scripts/tiles.py