Metadata-Version: 1.0
Name: gips
Version: 0.8.0rc4
Summary: Geospatial Image Processing System
Home-page: UNKNOWN
Author: Matthew Hanson
Author-email: matt.a.hanson@gmail.com
License: UNKNOWN
Platform: UNKNOWN
